gidgetlab/__init__.py
gidgetlab/_version.py
gidgetlab/abc.py
gidgetlab/aiohttp.py
gidgetlab/exceptions.py
gidgetlab/httpx.py
gidgetlab/py.typed
gidgetlab/routing.py
gidgetlab/sansio.py
gidgetlab/tornado.py
gidgetlab-2.1.1.dist-info/licenses/LICENSE
gidgetlab-2.1.1.dist-info/METADATA
gidgetlab-2.1.1.dist-info/WHEEL
gidgetlab-2.1.1.dist-info/top_level.txt
gidgetlab-2.1.1.dist-info/RECORD
