Metadata-Version: 2.4
Name: gidgetlab
Version: 2.1.1
Summary: An async GitLab API library
Author-email: Benjamin Bertrand <beenje@gmail.com>
License:                                  Apache License
Project-URL: Homepage, https://gitlab.com/beenje/gidgetlab
Project-URL: Documentation, https://gidgetlab.readthedocs.io
Project-URL: Repository, https://gitlab.com/beenje/gidgetlab
Keywords: gitlab,sans-io,async
Classifier: Intended Audience :: Developers
Classifier: License :: OSI Approved :: Apache Software License
Classifier: Development Status :: 5 - Production/Stable
Classifier: Programming Language :: Python
Requires-Python: >=3.10
License-File: LICENSE
Provides-Extra: docs
Requires-Dist: sphinx>=4.0.0; extra == "docs"
Requires-Dist: sphinx-autodoc-typehints; extra == "docs"
Requires-Dist: sphinx-rtd-theme; extra == "docs"
Provides-Extra: tests
Requires-Dist: pytest>=3.0.0; extra == "tests"
Requires-Dist: pytest-asyncio; extra == "tests"
Requires-Dist: pytest-cov; extra == "tests"
Requires-Dist: pytest-aiohttp; extra == "tests"
Requires-Dist: importlib-resources; extra == "tests"
Provides-Extra: aiohttp
Requires-Dist: aiohttp; extra == "aiohttp"
Requires-Dist: cachetools; extra == "aiohttp"
Provides-Extra: httpx
Requires-Dist: httpx>=0.11.0; extra == "httpx"
Provides-Extra: tornado
Requires-Dist: tornado; extra == "tornado"
Provides-Extra: dev
Requires-Dist: sphinx>=4.0.0; extra == "dev"
Requires-Dist: sphinx-autodoc-typehints; extra == "dev"
Requires-Dist: sphinx-rtd-theme; extra == "dev"
Requires-Dist: pytest>=3.0.0; extra == "dev"
Requires-Dist: pytest-asyncio; extra == "dev"
Requires-Dist: pytest-cov; extra == "dev"
Requires-Dist: pytest-aiohttp; extra == "dev"
Requires-Dist: importlib-resources; extra == "dev"
Requires-Dist: aiohttp; extra == "dev"
Requires-Dist: cachetools; extra == "dev"
Requires-Dist: httpx>=0.11.0; extra == "dev"
Requires-Dist: tornado; extra == "dev"
Dynamic: license-file
